pykelihood/__init__.py
pykelihood/distributions.py
pykelihood/generic_types.py
pykelihood/kernels.py
pykelihood/metrics.py
pykelihood/parameters.py
pykelihood/profiler.py
pykelihood/utils.py
pykelihood/visualisation/__init__.py
pykelihood/visualisation/utils.py
pykelihood-0.4.1.dist-info/LICENSE
pykelihood-0.4.1.dist-info/METADATA
pykelihood-0.4.1.dist-info/WHEEL
pykelihood-0.4.1.dist-info/RECORD
