Metadata-Version: 2.1
Name: pykelihood
Version: 0.4.1
Summary: Intuitive syntax for complex statistical model fitting and parameter sensitivity analysis.
Home-page: https://github.com/OpheliaMiralles/pykelihood
License: MIT
Author: Ophélia Miralles
Author-email: ophelia.miralles@epfl.ch
Requires-Python: >=3.7.1
Classifier: Development Status :: 3 - Alpha
Classifier: Intended Audience :: Science/Research
Classifier: License :: OSI Approved :: MIT License
Classifier: Programming Language :: Python :: 3
Classifier: Programming Language :: Python :: 3.8
Classifier: Programming Language :: Python :: 3.9
Classifier: Programming Language :: Python :: 3.10
Classifier: Programming Language :: Python :: 3.11
Classifier: Topic :: Scientific/Engineering
Requires-Dist: cached-property (>=1.5.2) ; python_version < "3.8"
Requires-Dist: numpy (>=1.16.5)
Requires-Dist: pandas (>=1.2.1)
Requires-Dist: scipy (>=1.5.3)
Project-URL: Repository, https://github.com/OpheliaMiralles/pykelihood
